nam_entropy/__init__.py
nam_entropy/bin_distribution_plots.py
nam_entropy/data_prep.py
nam_entropy/h.py
nam_entropy/integrated_distribution_2d_sampler.py
nam_entropy/make_data.py
nam_entropy/utils.py
nam_entropy-0.1.1.dist-info/LICENSE
nam_entropy-0.1.1.dist-info/METADATA
nam_entropy-0.1.1.dist-info/WHEEL
nam_entropy-0.1.1.dist-info/RECORD
