Metadata-Version: 2.3
Name: nam-entropy
Version: 0.1.1
Summary: 
Author: Jonathan Hanke
Author-email: jonhanke@princeton.edu
Requires-Python: >=3.12,<3.14
Classifier: Programming Language :: Python :: 3
Classifier: Programming Language :: Python :: 3.12
Classifier: Programming Language :: Python :: 3.13
Requires-Dist: attr (>=0.3.2,<0.4.0)
Requires-Dist: entmax (>=1.3,<2.0)
Requires-Dist: ipywidgets (>=8.1.7,<9.0.0)
Requires-Dist: numpy (>=2.3.3,<3.0.0)
Requires-Dist: pandas (>=2.3.2,<3.0.0)
Requires-Dist: pytest (>=8.4.2,<9.0.0)
Requires-Dist: python-dotenv (>=1.1.1,<2.0.0)
Requires-Dist: scikit-learn (>=1.7.2,<2.0.0)
Requires-Dist: torch (>=2.8.0,<3.0.0)
